s2clientprotocol/__init__.py
s2clientprotocol/build.py
s2clientprotocol/common_pb2.py
s2clientprotocol/data_pb2.py
s2clientprotocol/debug_pb2.py
s2clientprotocol/error_pb2.py
s2clientprotocol/query_pb2.py
s2clientprotocol/raw_pb2.py
s2clientprotocol/sc2api_pb2.py
s2clientprotocol/score_pb2.py
s2clientprotocol/spatial_pb2.py
s2clientprotocol/ui_pb2.py
s2clientprotocol-5.0.15.95299.0.dist-info/METADATA
s2clientprotocol-5.0.15.95299.0.dist-info/WHEEL
s2clientprotocol-5.0.15.95299.0.dist-info/top_level.txt
s2clientprotocol-5.0.15.95299.0.dist-info/RECORD
